setup.py
dev_tip/__init__.py
devtip.egg-info/PKG-INFO
devtip.egg-info/SOURCES.txt
devtip.egg-info/dependency_links.txt
devtip.egg-info/top_level.txt
test/test_foo.py