Metadata-Version: 1.1
Name: devtip
Version: 0.1.0
Summary: Very helpful functions.
Home-page: UNKNOWN
Author: Grzegorz Chlebus
Author-email: grzegorz.chlebus@mevis.fraunhofer.de
License: BSD 3-Clause
Keywords: foo add
Platform: UNKNOWN
Classifier: Development Status :: 4 - Beta
Classifier: Topic :: Utilities
Classifier: Programming Language :: Python
Classifier: License :: OSI Approved :: BSD License
